ionicsdk/COMMIT
ionicsdk/VERSION
ionicsdk/__init__.py
ionicsdk/_agent.py
ionicsdk/_chunkcipher.py
ionicsdk/_common.py
ionicsdk/_coverpage.py
ionicsdk/_cryptocipher.py
ionicsdk/_cryptoutil.py
ionicsdk/_filecipher.py
ionicsdk/_keyvault.py
ionicsdk/_log.py
ionicsdk/_private.py
ionicsdk/_profilemanager.py
ionicsdk/_secretshare.py
ionicsdk/_services.py
ionicsdk/_util.py
ionicsdk/agent.py
ionicsdk/chunkcipher.py
ionicsdk/common.py
ionicsdk/coverpage.py
ionicsdk/cryptocipher.py
ionicsdk/cryptoutil.py
ionicsdk/errors.py
ionicsdk/exceptions.py
ionicsdk/filecipher.py
ionicsdk/keyvault.py
ionicsdk/log.py
ionicsdk/profilemanager.py
ionicsdk/secretshare.py
ionicsdk/services.py
ionicsdk/lib/__init__.py
ionicsdk/lib/libCryptoAbstractLibFips.dylib
ionicsdk/lib/libCryptoAbstractLibFips.dylib.asc
ionicsdk/lib/libCryptoAbstractLibFips.so
ionicsdk/lib/libCryptoAbstractLibFips.so.asc
ionicsdk/lib/libCryptoAbstractLibPlatform.dylib
ionicsdk/lib/libCryptoAbstractLibPlatform.dylib.asc
ionicsdk/lib/libCryptoAbstractLibPlatform.so
ionicsdk/lib/libCryptoAbstractLibPlatform.so.asc
ionicsdk/lib/libISAgentSDKC.dylib
ionicsdk/lib/libISAgentSDKC.dylib.asc
ionicsdk/lib/libISAgentSDKC.so
ionicsdk/lib/libISAgentSDKC.so.asc
ionicsdk/lib/Win32/CryptoAbstractLibFips.dll
ionicsdk/lib/Win32/CryptoAbstractLibFips.dll.asc
ionicsdk/lib/Win32/CryptoAbstractLibPlatform.dll
ionicsdk/lib/Win32/CryptoAbstractLibPlatform.dll.asc
ionicsdk/lib/Win32/ISAgentSDKC.dll
ionicsdk/lib/Win32/ISAgentSDKC.dll.asc
ionicsdk/lib/Win32/__init__.py
ionicsdk/lib/x64/CryptoAbstractLibFips.dll
ionicsdk/lib/x64/CryptoAbstractLibFips.dll.asc
ionicsdk/lib/x64/CryptoAbstractLibPlatform.dll
ionicsdk/lib/x64/CryptoAbstractLibPlatform.dll.asc
ionicsdk/lib/x64/ISAgentSDKC.dll
ionicsdk/lib/x64/ISAgentSDKC.dll.asc
ionicsdk/lib/x64/__init__.py
ionicsdk-2.1.2.5.dist-info/LICENSE.md
ionicsdk-2.1.2.5.dist-info/METADATA
ionicsdk-2.1.2.5.dist-info/WHEEL
ionicsdk-2.1.2.5.dist-info/top_level.txt
ionicsdk-2.1.2.5.dist-info/RECORD
