Metadata-Version: 2.1
Name: ionicsdk
Version: 2.1.2.5
Summary: Ionic Machina Client SDK
Home-page: https://ionic.com/developers/
Author: Ionic Security Inc.
Author-email: dev@ionic.com
License: License Agreement for Ionic Resources
Project-URL: SDK Documentation, https://dev.ionic.com/sdk/docs/ionic_platform_sdk?language=python
Keywords: encryption user-authentication cryptography key-management data-security
Platform: UNKNOWN
Classifier: Development Status :: 5 - Production/Stable
Classifier: Intended Audience :: Developers
Classifier: Topic :: Software Development :: Libraries :: Python Modules
Classifier: License :: Other/Proprietary License
Classifier: Programming Language :: Python
Classifier: Programming Language :: Python :: 3
Classifier: Operating System :: Microsoft :: Windows :: Windows 10
Classifier: Operating System :: Microsoft :: Windows :: Windows 8.1
Classifier: Operating System :: Microsoft :: Windows :: Windows 8
Classifier: Operating System :: MacOS :: MacOS X
Classifier: Operating System :: POSIX :: Linux
